[
  {
    "id": "EVT-0000",
    "timestamp": "2026-02-01T10:42:37.350Z",
    "relativeMs": 131,
    "type": "action-start",
    "origin": "system",
    "correlationId": "COR-0000",
    "data": {
      "name": "rest.get",
      "component": null,
      "context": {
        "ui": {
          "route": "/config",
          "query": ""
        },
        "platform": "web",
        "featureFlags": {
          "hvsc_enabled": true
        },
        "playback": {
          "queueLength": 0,
          "currentIndex": -1,
          "currentItemId": null,
          "isPlaying": false,
          "elapsedMs": 0,
          "durationMs": null
        },
        "device": {
          "deviceId": null,
          "connectionState": "UNKNOWN"
        }
      }
    }
  },
  {
    "id": "EVT-0001",
    "timestamp": "2026-02-01T10:42:37.352Z",
    "relativeMs": 133,
    "type": "device-guard",
    "origin": "automatic",
    "correlationId": "COR-0000",
    "data": {
      "decision": "block",
      "reason": "state",
      "state": "UNKNOWN"
    }
  },
  {
    "id": "EVT-0002",
    "timestamp": "2026-02-01T10:42:37.358Z",
    "relativeMs": 139,
    "type": "action-start",
    "origin": "system",
    "correlationId": "COR-0001",
    "data": {
      "name": "rest.get",
      "component": null,
      "context": {
        "ui": {
          "route": "/config",
          "query": ""
        },
        "platform": "web",
        "featureFlags": {
          "hvsc_enabled": true
        },
        "playback": {
          "queueLength": 0,
          "currentIndex": -1,
          "currentItemId": null,
          "isPlaying": false,
          "elapsedMs": 0,
          "durationMs": null
        },
        "device": {
          "deviceId": null,
          "connectionState": "UNKNOWN"
        }
      }
    }
  },
  {
    "id": "EVT-0003",
    "timestamp": "2026-02-01T10:42:37.358Z",
    "relativeMs": 139,
    "type": "device-guard",
    "origin": "automatic",
    "correlationId": "COR-0001",
    "data": {
      "decision": "block",
      "reason": "state",
      "state": "UNKNOWN"
    }
  },
  {
    "id": "EVT-0004",
    "timestamp": "2026-02-01T10:42:37.358Z",
    "relativeMs": 139,
    "type": "error",
    "origin": "system",
    "correlationId": "COR-0000",
    "data": {
      "message": "Device not ready for requests",
      "name": "Error"
    }
  },
  {
    "id": "EVT-0005",
    "timestamp": "2026-02-01T10:42:37.358Z",
    "relativeMs": 139,
    "type": "action-end",
    "origin": "system",
    "correlationId": "COR-0000",
    "data": {
      "status": "error",
      "error": "Device not ready for requests"
    }
  },
  {
    "id": "EVT-0006",
    "timestamp": "2026-02-01T10:42:37.358Z",
    "relativeMs": 139,
    "type": "error",
    "origin": "system",
    "correlationId": "COR-0001",
    "data": {
      "message": "Device not ready for requests",
      "name": "Error"
    }
  },
  {
    "id": "EVT-0007",
    "timestamp": "2026-02-01T10:42:37.359Z",
    "relativeMs": 140,
    "type": "action-end",
    "origin": "system",
    "correlationId": "COR-0001",
    "data": {
      "status": "error",
      "error": "Device not ready for requests"
    }
  },
  {
    "id": "EVT-0008",
    "timestamp": "2026-02-01T10:42:37.359Z",
    "relativeMs": 140,
    "type": "action-start",
    "origin": "system",
    "correlationId": "COR-0002",
    "data": {
      "name": "rest.get",
      "component": null,
      "context": {
        "ui": {
          "route": "/config",
          "query": ""
        },
        "platform": "web",
        "featureFlags": {
          "hvsc_enabled": true
        },
        "playback": {
          "queueLength": 0,
          "currentIndex": -1,
          "currentItemId": null,
          "isPlaying": false,
          "elapsedMs": 0,
          "durationMs": null
        },
        "device": {
          "deviceId": null,
          "connectionState": "DISCOVERING"
        }
      }
    }
  },
  {
    "id": "EVT-0009",
    "timestamp": "2026-02-01T10:42:37.360Z",
    "relativeMs": 141,
    "type": "backend-decision",
    "origin": "automatic",
    "correlationId": "COR-0002",
    "data": {
      "selectedTarget": "external-mock",
      "reason": "test-mode"
    }
  },
  {
    "id": "EVT-0010",
    "timestamp": "2026-02-01T10:42:37.360Z",
    "relativeMs": 141,
    "type": "rest-request",
    "origin": "system",
    "correlationId": "COR-0002",
    "data": {
      "method": "GET",
      "url": "http://127.0.0.1:41889/v1/info",
      "normalizedUrl": "/v1/info",
      "headers": {
        "Content-Type": "application/json",
        "X-C64U-Host": "127.0.0.1:41889"
      },
      "body": null,
      "target": "external-mock"
    }
  },
  {
    "id": "EVT-0011",
    "timestamp": "2026-02-01T10:42:37.388Z",
    "relativeMs": 169,
    "type": "rest-response",
    "origin": "system",
    "correlationId": "COR-0002",
    "data": {
      "status": 200,
      "body": {
        "product": "C64 Ultimate",
        "firmware_version": "3.12.0",
        "fpga_version": "1.0.0",
        "core_version": "1.0.0",
        "hostname": "c64u",
        "unique_id": "TEST-123",
        "errors": []
      },
      "durationMs": 26,
      "error": null
    }
  },
  {
    "id": "EVT-0012",
    "timestamp": "2026-02-01T10:42:37.389Z",
    "relativeMs": 170,
    "type": "action-end",
    "origin": "system",
    "correlationId": "COR-0002",
    "data": {
      "status": "success",
      "error": null
    }
  },
  {
    "id": "EVT-0013",
    "timestamp": "2026-02-01T10:42:38.364Z",
    "relativeMs": 1145,
    "type": "action-start",
    "origin": "system",
    "correlationId": "COR-0003",
    "data": {
      "name": "rest.get",
      "component": null,
      "context": {
        "ui": {
          "route": "/config",
          "query": ""
        },
        "platform": "web",
        "featureFlags": {
          "hvsc_enabled": true
        },
        "playback": {
          "queueLength": 0,
          "currentIndex": -1,
          "currentItemId": null,
          "isPlaying": false,
          "elapsedMs": 0,
          "durationMs": null
        },
        "device": {
          "deviceId": null,
          "connectionState": "REAL_CONNECTED"
        }
      }
    }
  },
  {
    "id": "EVT-0014",
    "timestamp": "2026-02-01T10:42:38.364Z",
    "relativeMs": 1145,
    "type": "backend-decision",
    "origin": "automatic",
    "correlationId": "COR-0003",
    "data": {
      "selectedTarget": "external-mock",
      "reason": "test-mode"
    }
  },
  {
    "id": "EVT-0015",
    "timestamp": "2026-02-01T10:42:38.364Z",
    "relativeMs": 1145,
    "type": "rest-request",
    "origin": "system",
    "correlationId": "COR-0003",
    "data": {
      "method": "GET",
      "url": "http://127.0.0.1:41889/v1/configs",
      "normalizedUrl": "/v1/configs",
      "headers": {
        "Content-Type": "application/json",
        "X-C64U-Host": "127.0.0.1:41889"
      },
      "body": null,
      "target": "external-mock"
    }
  },
  {
    "id": "EVT-0016",
    "timestamp": "2026-02-01T10:42:38.364Z",
    "relativeMs": 1145,
    "type": "action-start",
    "origin": "system",
    "correlationId": "COR-0004",
    "data": {
      "name": "rest.get",
      "component": null,
      "context": {
        "ui": {
          "route": "/config",
          "query": ""
        },
        "platform": "web",
        "featureFlags": {
          "hvsc_enabled": true
        },
        "playback": {
          "queueLength": 0,
          "currentIndex": -1,
          "currentItemId": null,
          "isPlaying": false,
          "elapsedMs": 0,
          "durationMs": null
        },
        "device": {
          "deviceId": null,
          "connectionState": "BUSY"
        }
      }
    }
  },
  {
    "id": "EVT-0017",
    "timestamp": "2026-02-01T10:42:38.368Z",
    "relativeMs": 1149,
    "type": "rest-response",
    "origin": "system",
    "correlationId": "COR-0003",
    "data": {
      "status": 200,
      "body": {
        "categories": [
          "U64 Specific Settings",
          "Audio Mixer",
          "UltiSID Configuration",
          "Drive A Settings",
          "Drive B Settings"
        ],
        "errors": []
      },
      "durationMs": 4,
      "error": null
    }
  },
  {
    "id": "EVT-0018",
    "timestamp": "2026-02-01T10:42:38.368Z",
    "relativeMs": 1149,
    "type": "action-end",
    "origin": "system",
    "correlationId": "COR-0003",
    "data": {
      "status": "success",
      "error": null
    }
  },
  {
    "id": "EVT-0019",
    "timestamp": "2026-02-01T10:42:38.368Z",
    "relativeMs": 1149,
    "type": "backend-decision",
    "origin": "automatic",
    "correlationId": "COR-0004",
    "data": {
      "selectedTarget": "external-mock",
      "reason": "test-mode"
    }
  },
  {
    "id": "EVT-0020",
    "timestamp": "2026-02-01T10:42:38.369Z",
    "relativeMs": 1150,
    "type": "rest-request",
    "origin": "system",
    "correlationId": "COR-0004",
    "data": {
      "method": "GET",
      "url": "http://127.0.0.1:41889/v1/info",
      "normalizedUrl": "/v1/info",
      "headers": {
        "Content-Type": "application/json",
        "X-C64U-Host": "127.0.0.1:41889"
      },
      "body": null,
      "target": "external-mock"
    }
  },
  {
    "id": "EVT-0021",
    "timestamp": "2026-02-01T10:42:38.407Z",
    "relativeMs": 1188,
    "type": "rest-response",
    "origin": "system",
    "correlationId": "COR-0004",
    "data": {
      "status": 200,
      "body": {
        "product": "C64 Ultimate",
        "firmware_version": "3.12.0",
        "fpga_version": "1.0.0",
        "core_version": "1.0.0",
        "hostname": "c64u",
        "unique_id": "TEST-123",
        "errors": []
      },
      "durationMs": 16,
      "error": null
    }
  },
  {
    "id": "EVT-0022",
    "timestamp": "2026-02-01T10:42:38.407Z",
    "relativeMs": 1188,
    "type": "action-end",
    "origin": "system",
    "correlationId": "COR-0004",
    "data": {
      "status": "success",
      "error": null
    }
  },
  {
    "id": "EVT-0023",
    "timestamp": "2026-02-01T10:42:38.830Z",
    "relativeMs": 1611,
    "type": "action-start",
    "origin": "user",
    "correlationId": "COR-0005",
    "data": {
      "name": "click U64 Specific Settings",
      "component": "GlobalInteraction",
      "context": {
        "ui": {
          "route": "/config",
          "query": ""
        },
        "platform": "web",
        "featureFlags": {
          "hvsc_enabled": true
        },
        "playback": {
          "queueLength": 0,
          "currentIndex": -1,
          "currentItemId": null,
          "isPlaying": false,
          "elapsedMs": 0,
          "durationMs": null
        },
        "device": {
          "deviceId": "TEST-123",
          "connectionState": "REAL_CONNECTED"
        }
      }
    }
  },
  {
    "id": "EVT-0024",
    "timestamp": "2026-02-01T10:42:38.831Z",
    "relativeMs": 1612,
    "type": "action-end",
    "origin": "user",
    "correlationId": "COR-0005",
    "data": {
      "status": "success",
      "error": null
    }
  },
  {
    "id": "EVT-0025",
    "timestamp": "2026-02-01T10:42:38.833Z",
    "relativeMs": 1614,
    "type": "action-start",
    "origin": "user",
    "correlationId": "COR-0006",
    "data": {
      "name": "toggle U64 Specific Settings",
      "component": "ConfigSection",
      "context": {
        "ui": {
          "route": "/config",
          "query": ""
        },
        "platform": "web",
        "featureFlags": {
          "hvsc_enabled": true
        },
        "playback": {
          "queueLength": 0,
          "currentIndex": -1,
          "currentItemId": null,
          "isPlaying": false,
          "elapsedMs": 0,
          "durationMs": null
        },
        "device": {
          "deviceId": "TEST-123",
          "connectionState": "REAL_CONNECTED"
        }
      }
    }
  },
  {
    "id": "EVT-0026",
    "timestamp": "2026-02-01T10:42:38.837Z",
    "relativeMs": 1618,
    "type": "action-start",
    "origin": "system",
    "correlationId": "COR-0007",
    "data": {
      "name": "rest.get",
      "component": null,
      "context": {
        "ui": {
          "route": "/config",
          "query": ""
        },
        "platform": "web",
        "featureFlags": {
          "hvsc_enabled": true
        },
        "playback": {
          "queueLength": 0,
          "currentIndex": -1,
          "currentItemId": null,
          "isPlaying": false,
          "elapsedMs": 0,
          "durationMs": null
        },
        "device": {
          "deviceId": "TEST-123",
          "connectionState": "REAL_CONNECTED"
        }
      }
    }
  },
  {
    "id": "EVT-0027",
    "timestamp": "2026-02-01T10:42:38.838Z",
    "relativeMs": 1619,
    "type": "backend-decision",
    "origin": "automatic",
    "correlationId": "COR-0007",
    "data": {
      "selectedTarget": "external-mock",
      "reason": "test-mode"
    }
  },
  {
    "id": "EVT-0028",
    "timestamp": "2026-02-01T10:42:38.838Z",
    "relativeMs": 1619,
    "type": "rest-request",
    "origin": "system",
    "correlationId": "COR-0007",
    "data": {
      "method": "GET",
      "url": "http://127.0.0.1:41889/v1/configs/U64%20Specific%20Settings",
      "normalizedUrl": "/v1/configs/U64%20Specific%20Settings",
      "headers": {
        "Content-Type": "application/json",
        "X-C64U-Host": "127.0.0.1:41889"
      },
      "body": null,
      "target": "external-mock"
    }
  },
  {
    "id": "EVT-0029",
    "timestamp": "2026-02-01T10:42:38.839Z",
    "relativeMs": 1620,
    "type": "action-end",
    "origin": "user",
    "correlationId": "COR-0006",
    "data": {
      "status": "success",
      "error": null
    }
  },
  {
    "id": "EVT-0030",
    "timestamp": "2026-02-01T10:42:38.873Z",
    "relativeMs": 1654,
    "type": "rest-response",
    "origin": "system",
    "correlationId": "COR-0007",
    "data": {
      "status": 200,
      "body": {
        "U64 Specific Settings": {
          "items": {
            "System Mode": {
              "selected": "PAL",
              "options": [
                "PAL",
                "NTSC",
                "PAL-60",
                "NTSC-50",
                "PAL-60/L",
                "NTSC-50/L"
              ]
            },
            "Digital Video Mode": {
              "selected": "Auto",
              "options": [
                "Auto",
                "HDMI",
                "DVI"
              ]
            },
            "HDMI Scan lines": {
              "selected": "Enabled",
              "options": [
                "Disabled",
                "Enabled"
              ]
            }
          }
        },
        "errors": []
      },
      "durationMs": 20,
      "error": null
    }
  },
  {
    "id": "EVT-0031",
    "timestamp": "2026-02-01T10:42:38.874Z",
    "relativeMs": 1655,
    "type": "action-end",
    "origin": "system",
    "correlationId": "COR-0007",
    "data": {
      "status": "success",
      "error": null
    }
  },
  {
    "id": "EVT-0032",
    "timestamp": "2026-02-01T10:42:39.306Z",
    "relativeMs": 2087,
    "type": "action-start",
    "origin": "user",
    "correlationId": "COR-0008",
    "data": {
      "name": "select Select [NTSC]",
      "component": "Select",
      "context": {
        "ui": {
          "route": "/config",
          "query": ""
        },
        "platform": "web",
        "featureFlags": {
          "hvsc_enabled": true
        },
        "playback": {
          "queueLength": 0,
          "currentIndex": -1,
          "currentItemId": null,
          "isPlaying": false,
          "elapsedMs": 0,
          "durationMs": null
        },
        "device": {
          "deviceId": null,
          "connectionState": "READY"
        }
      }
    }
  },
  {
    "id": "EVT-0033",
    "timestamp": "2026-02-01T10:42:39.312Z",
    "relativeMs": 2093,
    "type": "action-end",
    "origin": "user",
    "correlationId": "COR-0008",
    "data": {
      "status": "success",
      "error": null
    }
  },
  {
    "id": "EVT-0034",
    "timestamp": "2026-02-01T10:42:39.313Z",
    "relativeMs": 2094,
    "type": "action-start",
    "origin": "system",
    "correlationId": "COR-0009",
    "data": {
      "name": "rest.put",
      "component": null,
      "context": {
        "ui": {
          "route": "/config",
          "query": ""
        },
        "platform": "web",
        "featureFlags": {
          "hvsc_enabled": true
        },
        "playback": {
          "queueLength": 0,
          "currentIndex": -1,
          "currentItemId": null,
          "isPlaying": false,
          "elapsedMs": 0,
          "durationMs": null
        },
        "device": {
          "deviceId": null,
          "connectionState": "READY"
        }
      }
    }
  },
  {
    "id": "EVT-0035",
    "timestamp": "2026-02-01T10:42:39.313Z",
    "relativeMs": 2094,
    "type": "backend-decision",
    "origin": "automatic",
    "correlationId": "COR-0009",
    "data": {
      "selectedTarget": "external-mock",
      "reason": "test-mode"
    }
  },
  {
    "id": "EVT-0036",
    "timestamp": "2026-02-01T10:42:39.314Z",
    "relativeMs": 2095,
    "type": "rest-request",
    "origin": "system",
    "correlationId": "COR-0009",
    "data": {
      "method": "PUT",
      "url": "http://127.0.0.1:41889/v1/configs/U64%20Specific%20Settings/System%20Mode?value=NTSC",
      "normalizedUrl": "/v1/configs/U64%20Specific%20Settings/System%20Mode?value=NTSC",
      "headers": {
        "Content-Type": "application/json",
        "X-C64U-Host": "127.0.0.1:41889"
      },
      "body": null,
      "target": "external-mock"
    }
  },
  {
    "id": "EVT-0037",
    "timestamp": "2026-02-01T10:42:39.352Z",
    "relativeMs": 2133,
    "type": "rest-response",
    "origin": "system",
    "correlationId": "COR-0009",
    "data": {
      "status": 200,
      "body": {
        "errors": []
      },
      "durationMs": 20,
      "error": null
    }
  },
  {
    "id": "EVT-0038",
    "timestamp": "2026-02-01T10:42:39.353Z",
    "relativeMs": 2134,
    "type": "action-end",
    "origin": "system",
    "correlationId": "COR-0009",
    "data": {
      "status": "success",
      "error": null
    }
  },
  {
    "id": "EVT-0039",
    "timestamp": "2026-02-01T10:42:39.354Z",
    "relativeMs": 2135,
    "type": "action-start",
    "origin": "system",
    "correlationId": "COR-0010",
    "data": {
      "name": "rest.get",
      "component": null,
      "context": {
        "ui": {
          "route": "/config",
          "query": ""
        },
        "platform": "web",
        "featureFlags": {
          "hvsc_enabled": true
        },
        "playback": {
          "queueLength": 0,
          "currentIndex": -1,
          "currentItemId": null,
          "isPlaying": false,
          "elapsedMs": 0,
          "durationMs": null
        },
        "device": {
          "deviceId": null,
          "connectionState": "READY"
        }
      }
    }
  },
  {
    "id": "EVT-0040",
    "timestamp": "2026-02-01T10:42:39.355Z",
    "relativeMs": 2136,
    "type": "backend-decision",
    "origin": "automatic",
    "correlationId": "COR-0010",
    "data": {
      "selectedTarget": "external-mock",
      "reason": "test-mode"
    }
  },
  {
    "id": "EVT-0041",
    "timestamp": "2026-02-01T10:42:39.356Z",
    "relativeMs": 2137,
    "type": "rest-request",
    "origin": "system",
    "correlationId": "COR-0010",
    "data": {
      "method": "GET",
      "url": "http://127.0.0.1:41889/v1/configs/U64%20Specific%20Settings",
      "normalizedUrl": "/v1/configs/U64%20Specific%20Settings",
      "headers": {
        "Content-Type": "application/json",
        "X-C64U-Host": "127.0.0.1:41889"
      },
      "body": null,
      "target": "external-mock"
    }
  },
  {
    "id": "EVT-0042",
    "timestamp": "2026-02-01T10:42:39.392Z",
    "relativeMs": 2173,
    "type": "rest-response",
    "origin": "system",
    "correlationId": "COR-0010",
    "data": {
      "status": 200,
      "body": {
        "U64 Specific Settings": {
          "items": {
            "System Mode": {
              "selected": "NTSC",
              "options": [
                "PAL",
                "NTSC",
                "PAL-60",
                "NTSC-50",
                "PAL-60/L",
                "NTSC-50/L"
              ]
            },
            "Digital Video Mode": {
              "selected": "Auto",
              "options": [
                "Auto",
                "HDMI",
                "DVI"
              ]
            },
            "HDMI Scan lines": {
              "selected": "Enabled",
              "options": [
                "Disabled",
                "Enabled"
              ]
            }
          }
        },
        "errors": []
      },
      "durationMs": 21,
      "error": null
    }
  },
  {
    "id": "EVT-0043",
    "timestamp": "2026-02-01T10:42:39.393Z",
    "relativeMs": 2174,
    "type": "action-end",
    "origin": "system",
    "correlationId": "COR-0010",
    "data": {
      "status": "success",
      "error": null
    }
  },
  {
    "id": "EVT-0044",
    "timestamp": "2026-02-01T10:42:39.510Z",
    "relativeMs": 2291,
    "type": "action-start",
    "origin": "user",
    "correlationId": "COR-0011",
    "data": {
      "name": "click HDMI Scan lines checkbox",
      "component": "GlobalInteraction",
      "context": {
        "ui": {
          "route": "/config",
          "query": ""
        },
        "platform": "web",
        "featureFlags": {
          "hvsc_enabled": true
        },
        "playback": {
          "queueLength": 0,
          "currentIndex": -1,
          "currentItemId": null,
          "isPlaying": false,
          "elapsedMs": 0,
          "durationMs": null
        },
        "device": {
          "deviceId": null,
          "connectionState": "READY"
        }
      }
    }
  },
  {
    "id": "EVT-0045",
    "timestamp": "2026-02-01T10:42:39.511Z",
    "relativeMs": 2292,
    "type": "action-end",
    "origin": "user",
    "correlationId": "COR-0011",
    "data": {
      "status": "success",
      "error": null
    }
  },
  {
    "id": "EVT-0046",
    "timestamp": "2026-02-01T10:42:39.511Z",
    "relativeMs": 2292,
    "type": "action-start",
    "origin": "user",
    "correlationId": "COR-0012",
    "data": {
      "name": "toggle HDMI Scan lines checkbox [false]",
      "component": "Checkbox",
      "context": {
        "ui": {
          "route": "/config",
          "query": ""
        },
        "platform": "web",
        "featureFlags": {
          "hvsc_enabled": true
        },
        "playback": {
          "queueLength": 0,
          "currentIndex": -1,
          "currentItemId": null,
          "isPlaying": false,
          "elapsedMs": 0,
          "durationMs": null
        },
        "device": {
          "deviceId": null,
          "connectionState": "READY"
        }
      }
    }
  },
  {
    "id": "EVT-0047",
    "timestamp": "2026-02-01T10:42:39.514Z",
    "relativeMs": 2295,
    "type": "action-end",
    "origin": "user",
    "correlationId": "COR-0012",
    "data": {
      "status": "success",
      "error": null
    }
  },
  {
    "id": "EVT-0048",
    "timestamp": "2026-02-01T10:42:39.671Z",
    "relativeMs": 2452,
    "type": "action-start",
    "origin": "user",
    "correlationId": "COR-0013",
    "data": {
      "name": "click Audio Mixer",
      "component": "GlobalInteraction",
      "context": {
        "ui": {
          "route": "/config",
          "query": ""
        },
        "platform": "web",
        "featureFlags": {
          "hvsc_enabled": true
        },
        "playback": {
          "queueLength": 0,
          "currentIndex": -1,
          "currentItemId": null,
          "isPlaying": false,
          "elapsedMs": 0,
          "durationMs": null
        },
        "device": {
          "deviceId": null,
          "connectionState": "READY"
        }
      }
    }
  },
  {
    "id": "EVT-0049",
    "timestamp": "2026-02-01T10:42:39.672Z",
    "relativeMs": 2453,
    "type": "action-end",
    "origin": "user",
    "correlationId": "COR-0013",
    "data": {
      "status": "success",
      "error": null
    }
  },
  {
    "id": "EVT-0050",
    "timestamp": "2026-02-01T10:42:39.673Z",
    "relativeMs": 2454,
    "type": "action-start",
    "origin": "user",
    "correlationId": "COR-0014",
    "data": {
      "name": "toggle Audio Mixer",
      "component": "ConfigSection",
      "context": {
        "ui": {
          "route": "/config",
          "query": ""
        },
        "platform": "web",
        "featureFlags": {
          "hvsc_enabled": true
        },
        "playback": {
          "queueLength": 0,
          "currentIndex": -1,
          "currentItemId": null,
          "isPlaying": false,
          "elapsedMs": 0,
          "durationMs": null
        },
        "device": {
          "deviceId": null,
          "connectionState": "READY"
        }
      }
    }
  },
  {
    "id": "EVT-0051",
    "timestamp": "2026-02-01T10:42:39.675Z",
    "relativeMs": 2456,
    "type": "action-start",
    "origin": "system",
    "correlationId": "COR-0015",
    "data": {
      "name": "rest.get",
      "component": null,
      "context": {
        "ui": {
          "route": "/config",
          "query": ""
        },
        "platform": "web",
        "featureFlags": {
          "hvsc_enabled": true
        },
        "playback": {
          "queueLength": 0,
          "currentIndex": -1,
          "currentItemId": null,
          "isPlaying": false,
          "elapsedMs": 0,
          "durationMs": null
        },
        "device": {
          "deviceId": null,
          "connectionState": "READY"
        }
      }
    }
  },
  {
    "id": "EVT-0052",
    "timestamp": "2026-02-01T10:42:39.676Z",
    "relativeMs": 2457,
    "type": "backend-decision",
    "origin": "automatic",
    "correlationId": "COR-0015",
    "data": {
      "selectedTarget": "external-mock",
      "reason": "test-mode"
    }
  },
  {
    "id": "EVT-0053",
    "timestamp": "2026-02-01T10:42:39.677Z",
    "relativeMs": 2458,
    "type": "rest-request",
    "origin": "system",
    "correlationId": "COR-0015",
    "data": {
      "method": "GET",
      "url": "http://127.0.0.1:41889/v1/configs/Audio%20Mixer",
      "normalizedUrl": "/v1/configs/Audio%20Mixer",
      "headers": {
        "Content-Type": "application/json",
        "X-C64U-Host": "127.0.0.1:41889"
      },
      "body": null,
      "target": "external-mock"
    }
  },
  {
    "id": "EVT-0054",
    "timestamp": "2026-02-01T10:42:39.677Z",
    "relativeMs": 2458,
    "type": "action-end",
    "origin": "user",
    "correlationId": "COR-0014",
    "data": {
      "status": "success",
      "error": null
    }
  },
  {
    "id": "EVT-0055",
    "timestamp": "2026-02-01T10:42:39.721Z",
    "relativeMs": 2502,
    "type": "rest-response",
    "origin": "system",
    "correlationId": "COR-0015",
    "data": {
      "status": 200,
      "body": {
        "Audio Mixer": {
          "items": {
            "Vol UltiSid 1": {
              "selected": "OFF",
              "options": [
                "OFF",
                "+6 dB",
                "+5 dB",
                "+4 dB",
                "+3 dB",
                "+2 dB",
                "+1 dB",
                " 0 dB",
                "-1 dB",
                "-2 dB",
                "-3 dB",
                "-4 dB",
                "-5 dB",
                "-6 dB",
                "-7 dB",
                "-8 dB",
                "-9 dB",
                "-10 dB",
                "-11 dB",
                "-12 dB",
                "-13 dB",
                "-14 dB",
                "-15 dB",
                "-16 dB",
                "-17 dB",
                "-18 dB",
                "-24 dB",
                "-27 dB",
                "-30 dB",
                "-36 dB",
                "-42 dB"
              ]
            },
            "Vol UltiSid 2": {
              "selected": "+2 dB",
              "options": [
                "OFF",
                "+6 dB",
                "+5 dB",
                "+4 dB",
                "+3 dB",
                "+2 dB",
                "+1 dB",
                " 0 dB",
                "-1 dB",
                "-2 dB",
                "-3 dB",
                "-4 dB",
                "-5 dB",
                "-6 dB",
                "-7 dB",
                "-8 dB",
                "-9 dB",
                "-10 dB",
                "-11 dB",
                "-12 dB",
                "-13 dB",
                "-14 dB",
                "-15 dB",
                "-16 dB",
                "-17 dB",
                "-18 dB",
                "-24 dB",
                "-27 dB",
                "-30 dB",
                "-36 dB",
                "-42 dB"
              ]
            },
            "Vol Socket 1": {
              "selected": "-6 dB",
              "options": [
                "OFF",
                "+6 dB",
                "+5 dB",
                "+4 dB",
                "+3 dB",
                "+2 dB",
                "+1 dB",
                " 0 dB",
                "-1 dB",
                "-2 dB",
                "-3 dB",
                "-4 dB",
                "-5 dB",
                "-6 dB",
                "-7 dB",
                "-8 dB",
                "-9 dB",
                "-10 dB",
                "-11 dB",
                "-12 dB",
                "-13 dB",
                "-14 dB",
                "-15 dB",
                "-16 dB",
                "-17 dB",
                "-18 dB",
                "-24 dB",
                "-27 dB",
                "-30 dB",
                "-36 dB",
                "-42 dB"
              ]
            },
            "Vol Socket 2": {
              "selected": "+1 dB",
              "options": [
                "OFF",
                "+6 dB",
                "+5 dB",
                "+4 dB",
                "+3 dB",
                "+2 dB",
                "+1 dB",
                " 0 dB",
                "-1 dB",
                "-2 dB",
                "-3 dB",
                "-4 dB",
                "-5 dB",
                "-6 dB",
                "-7 dB",
                "-8 dB",
                "-9 dB",
                "-10 dB",
                "-11 dB",
                "-12 dB",
                "-13 dB",
                "-14 dB",
                "-15 dB",
                "-16 dB",
                "-17 dB",
                "-18 dB",
                "-24 dB",
                "-27 dB",
                "-30 dB",
                "-36 dB",
                "-42 dB"
              ]
            }
          }
        },
        "errors": []
      },
      "durationMs": 17,
      "error": null
    }
  },
  {
    "id": "EVT-0056",
    "timestamp": "2026-02-01T10:42:39.722Z",
    "relativeMs": 2503,
    "type": "action-end",
    "origin": "system",
    "correlationId": "COR-0015",
    "data": {
      "status": "success",
      "error": null
    }
  },
  {
    "id": "EVT-0057",
    "timestamp": "2026-02-01T10:42:39.836Z",
    "relativeMs": 2617,
    "type": "action-start",
    "origin": "system",
    "correlationId": "COR-0016",
    "data": {
      "name": "rest.put",
      "component": null,
      "context": {
        "ui": {
          "route": "/config",
          "query": ""
        },
        "platform": "web",
        "featureFlags": {
          "hvsc_enabled": true
        },
        "playback": {
          "queueLength": 0,
          "currentIndex": -1,
          "currentItemId": null,
          "isPlaying": false,
          "elapsedMs": 0,
          "durationMs": null
        },
        "device": {
          "deviceId": null,
          "connectionState": "READY"
        }
      }
    }
  },
  {
    "id": "EVT-0058",
    "timestamp": "2026-02-01T10:42:39.837Z",
    "relativeMs": 2618,
    "type": "backend-decision",
    "origin": "automatic",
    "correlationId": "COR-0016",
    "data": {
      "selectedTarget": "external-mock",
      "reason": "test-mode"
    }
  },
  {
    "id": "EVT-0059",
    "timestamp": "2026-02-01T10:42:39.837Z",
    "relativeMs": 2618,
    "type": "rest-request",
    "origin": "system",
    "correlationId": "COR-0016",
    "data": {
      "method": "PUT",
      "url": "http://127.0.0.1:41889/v1/configs/U64%20Specific%20Settings/HDMI%20Scan%20lines?value=Disabled",
      "normalizedUrl": "/v1/configs/U64%20Specific%20Settings/HDMI%20Scan%20lines?value=Disabled",
      "headers": {
        "Content-Type": "application/json",
        "X-C64U-Host": "127.0.0.1:41889"
      },
      "body": null,
      "target": "external-mock"
    }
  },
  {
    "id": "EVT-0060",
    "timestamp": "2026-02-01T10:42:39.920Z",
    "relativeMs": 2701,
    "type": "rest-response",
    "origin": "system",
    "correlationId": "COR-0016",
    "data": {
      "status": 200,
      "body": {
        "errors": []
      },
      "durationMs": 36,
      "error": null
    }
  },
  {
    "id": "EVT-0061",
    "timestamp": "2026-02-01T10:42:39.923Z",
    "relativeMs": 2704,
    "type": "action-end",
    "origin": "system",
    "correlationId": "COR-0016",
    "data": {
      "status": "success",
      "error": null
    }
  },
  {
    "id": "EVT-0062",
    "timestamp": "2026-02-01T10:42:39.924Z",
    "relativeMs": 2705,
    "type": "action-start",
    "origin": "system",
    "correlationId": "COR-0017",
    "data": {
      "name": "rest.get",
      "component": null,
      "context": {
        "ui": {
          "route": "/config",
          "query": ""
        },
        "platform": "web",
        "featureFlags": {
          "hvsc_enabled": true
        },
        "playback": {
          "queueLength": 0,
          "currentIndex": -1,
          "currentItemId": null,
          "isPlaying": false,
          "elapsedMs": 0,
          "durationMs": null
        },
        "device": {
          "deviceId": null,
          "connectionState": "READY"
        }
      }
    }
  },
  {
    "id": "EVT-0063",
    "timestamp": "2026-02-01T10:42:39.925Z",
    "relativeMs": 2706,
    "type": "backend-decision",
    "origin": "automatic",
    "correlationId": "COR-0017",
    "data": {
      "selectedTarget": "external-mock",
      "reason": "test-mode"
    }
  },
  {
    "id": "EVT-0064",
    "timestamp": "2026-02-01T10:42:39.925Z",
    "relativeMs": 2706,
    "type": "rest-request",
    "origin": "system",
    "correlationId": "COR-0017",
    "data": {
      "method": "GET",
      "url": "http://127.0.0.1:41889/v1/configs/U64%20Specific%20Settings",
      "normalizedUrl": "/v1/configs/U64%20Specific%20Settings",
      "headers": {
        "Content-Type": "application/json",
        "X-C64U-Host": "127.0.0.1:41889"
      },
      "body": null,
      "target": "external-mock"
    }
  },
  {
    "id": "EVT-0065",
    "timestamp": "2026-02-01T10:42:39.963Z",
    "relativeMs": 2744,
    "type": "rest-response",
    "origin": "system",
    "correlationId": "COR-0017",
    "data": {
      "status": 200,
      "body": {
        "U64 Specific Settings": {
          "items": {
            "System Mode": {
              "selected": "NTSC",
              "options": [
                "PAL",
                "NTSC",
                "PAL-60",
                "NTSC-50",
                "PAL-60/L",
                "NTSC-50/L"
              ]
            },
            "Digital Video Mode": {
              "selected": "Auto",
              "options": [
                "Auto",
                "HDMI",
                "DVI"
              ]
            },
            "HDMI Scan lines": {
              "selected": "Disabled",
              "options": [
                "Disabled",
                "Enabled"
              ]
            }
          }
        },
        "errors": []
      },
      "durationMs": 24,
      "error": null
    }
  },
  {
    "id": "EVT-0066",
    "timestamp": "2026-02-01T10:42:39.963Z",
    "relativeMs": 2744,
    "type": "action-end",
    "origin": "system",
    "correlationId": "COR-0017",
    "data": {
      "status": "success",
      "error": null
    }
  },
  {
    "id": "EVT-0067",
    "timestamp": "2026-02-01T10:42:40.877Z",
    "relativeMs": 3658,
    "type": "action-start",
    "origin": "user",
    "correlationId": "COR-0018",
    "data": {
      "name": "slide Vol UltiSid 1 slider [[30]]",
      "component": "Slider",
      "context": {
        "ui": {
          "route": "/config",
          "query": ""
        },
        "platform": "web",
        "featureFlags": {
          "hvsc_enabled": true
        },
        "playback": {
          "queueLength": 0,
          "currentIndex": -1,
          "currentItemId": null,
          "isPlaying": false,
          "elapsedMs": 0,
          "durationMs": null
        },
        "device": {
          "deviceId": null,
          "connectionState": "READY"
        }
      }
    }
  },
  {
    "id": "EVT-0068",
    "timestamp": "2026-02-01T10:42:40.879Z",
    "relativeMs": 3660,
    "type": "action-end",
    "origin": "user",
    "correlationId": "COR-0018",
    "data": {
      "status": "success",
      "error": null
    }
  },
  {
    "id": "EVT-0069",
    "timestamp": "2026-02-01T10:42:40.886Z",
    "relativeMs": 3667,
    "type": "action-start",
    "origin": "system",
    "correlationId": "COR-0019",
    "data": {
      "name": "rest.put",
      "component": null,
      "context": {
        "ui": {
          "route": "/config",
          "query": ""
        },
        "platform": "web",
        "featureFlags": {
          "hvsc_enabled": true
        },
        "playback": {
          "queueLength": 0,
          "currentIndex": -1,
          "currentItemId": null,
          "isPlaying": false,
          "elapsedMs": 0,
          "durationMs": null
        },
        "device": {
          "deviceId": null,
          "connectionState": "READY"
        }
      }
    }
  },
  {
    "id": "EVT-0070",
    "timestamp": "2026-02-01T10:42:40.887Z",
    "relativeMs": 3668,
    "type": "backend-decision",
    "origin": "automatic",
    "correlationId": "COR-0019",
    "data": {
      "selectedTarget": "external-mock",
      "reason": "test-mode"
    }
  },
  {
    "id": "EVT-0071",
    "timestamp": "2026-02-01T10:42:40.887Z",
    "relativeMs": 3668,
    "type": "rest-request",
    "origin": "system",
    "correlationId": "COR-0019",
    "data": {
      "method": "PUT",
      "url": "http://127.0.0.1:41889/v1/configs/Audio%20Mixer/Vol%20UltiSid%201?value=%2B6%20dB",
      "normalizedUrl": "/v1/configs/Audio%20Mixer/Vol%20UltiSid%201?value=%2B6%20dB",
      "headers": {
        "Content-Type": "application/json",
        "X-C64U-Host": "127.0.0.1:41889"
      },
      "body": null,
      "target": "external-mock"
    }
  },
  {
    "id": "EVT-0072",
    "timestamp": "2026-02-01T10:42:40.889Z",
    "relativeMs": 3670,
    "type": "action-start",
    "origin": "user",
    "correlationId": "COR-0020",
    "data": {
      "name": "click Vol UltiSid 1 slider",
      "component": "GlobalInteraction",
      "context": {
        "ui": {
          "route": "/config",
          "query": ""
        },
        "platform": "web",
        "featureFlags": {
          "hvsc_enabled": true
        },
        "playback": {
          "queueLength": 0,
          "currentIndex": -1,
          "currentItemId": null,
          "isPlaying": false,
          "elapsedMs": 0,
          "durationMs": null
        },
        "device": {
          "deviceId": null,
          "connectionState": "BUSY"
        }
      }
    }
  },
  {
    "id": "EVT-0073",
    "timestamp": "2026-02-01T10:42:40.890Z",
    "relativeMs": 3671,
    "type": "action-end",
    "origin": "user",
    "correlationId": "COR-0020",
    "data": {
      "status": "success",
      "error": null
    }
  },
  {
    "id": "EVT-0074",
    "timestamp": "2026-02-01T10:42:40.915Z",
    "relativeMs": 3696,
    "type": "rest-response",
    "origin": "system",
    "correlationId": "COR-0019",
    "data": {
      "status": 200,
      "body": {
        "errors": []
      },
      "durationMs": 14,
      "error": null
    }
  },
  {
    "id": "EVT-0075",
    "timestamp": "2026-02-01T10:42:40.917Z",
    "relativeMs": 3698,
    "type": "action-end",
    "origin": "system",
    "correlationId": "COR-0019",
    "data": {
      "status": "success",
      "error": null
    }
  },
  {
    "id": "EVT-0076",
    "timestamp": "2026-02-01T10:42:40.917Z",
    "relativeMs": 3698,
    "type": "action-start",
    "origin": "system",
    "correlationId": "COR-0021",
    "data": {
      "name": "rest.get",
      "component": null,
      "context": {
        "ui": {
          "route": "/config",
          "query": ""
        },
        "platform": "web",
        "featureFlags": {
          "hvsc_enabled": true
        },
        "playback": {
          "queueLength": 0,
          "currentIndex": -1,
          "currentItemId": null,
          "isPlaying": false,
          "elapsedMs": 0,
          "durationMs": null
        },
        "device": {
          "deviceId": null,
          "connectionState": "READY"
        }
      }
    }
  },
  {
    "id": "EVT-0077",
    "timestamp": "2026-02-01T10:42:40.918Z",
    "relativeMs": 3699,
    "type": "backend-decision",
    "origin": "automatic",
    "correlationId": "COR-0021",
    "data": {
      "selectedTarget": "external-mock",
      "reason": "test-mode"
    }
  },
  {
    "id": "EVT-0078",
    "timestamp": "2026-02-01T10:42:40.918Z",
    "relativeMs": 3699,
    "type": "rest-request",
    "origin": "system",
    "correlationId": "COR-0021",
    "data": {
      "method": "GET",
      "url": "http://127.0.0.1:41889/v1/configs/Audio%20Mixer",
      "normalizedUrl": "/v1/configs/Audio%20Mixer",
      "headers": {
        "Content-Type": "application/json",
        "X-C64U-Host": "127.0.0.1:41889"
      },
      "body": null,
      "target": "external-mock"
    }
  },
  {
    "id": "EVT-0079",
    "timestamp": "2026-02-01T10:42:40.954Z",
    "relativeMs": 3735,
    "type": "rest-response",
    "origin": "system",
    "correlationId": "COR-0021",
    "data": {
      "status": 200,
      "body": {
        "Audio Mixer": {
          "items": {
            "Vol UltiSid 1": {
              "selected": "+6 dB",
              "options": [
                "OFF",
                "+6 dB",
                "+5 dB",
                "+4 dB",
                "+3 dB",
                "+2 dB",
                "+1 dB",
                " 0 dB",
                "-1 dB",
                "-2 dB",
                "-3 dB",
                "-4 dB",
                "-5 dB",
                "-6 dB",
                "-7 dB",
                "-8 dB",
                "-9 dB",
                "-10 dB",
                "-11 dB",
                "-12 dB",
                "-13 dB",
                "-14 dB",
                "-15 dB",
                "-16 dB",
                "-17 dB",
                "-18 dB",
                "-24 dB",
                "-27 dB",
                "-30 dB",
                "-36 dB",
                "-42 dB"
              ]
            },
            "Vol UltiSid 2": {
              "selected": "+2 dB",
              "options": [
                "OFF",
                "+6 dB",
                "+5 dB",
                "+4 dB",
                "+3 dB",
                "+2 dB",
                "+1 dB",
                " 0 dB",
                "-1 dB",
                "-2 dB",
                "-3 dB",
                "-4 dB",
                "-5 dB",
                "-6 dB",
                "-7 dB",
                "-8 dB",
                "-9 dB",
                "-10 dB",
                "-11 dB",
                "-12 dB",
                "-13 dB",
                "-14 dB",
                "-15 dB",
                "-16 dB",
                "-17 dB",
                "-18 dB",
                "-24 dB",
                "-27 dB",
                "-30 dB",
                "-36 dB",
                "-42 dB"
              ]
            },
            "Vol Socket 1": {
              "selected": "-6 dB",
              "options": [
                "OFF",
                "+6 dB",
                "+5 dB",
                "+4 dB",
                "+3 dB",
                "+2 dB",
                "+1 dB",
                " 0 dB",
                "-1 dB",
                "-2 dB",
                "-3 dB",
                "-4 dB",
                "-5 dB",
                "-6 dB",
                "-7 dB",
                "-8 dB",
                "-9 dB",
                "-10 dB",
                "-11 dB",
                "-12 dB",
                "-13 dB",
                "-14 dB",
                "-15 dB",
                "-16 dB",
                "-17 dB",
                "-18 dB",
                "-24 dB",
                "-27 dB",
                "-30 dB",
                "-36 dB",
                "-42 dB"
              ]
            },
            "Vol Socket 2": {
              "selected": "+1 dB",
              "options": [
                "OFF",
                "+6 dB",
                "+5 dB",
                "+4 dB",
                "+3 dB",
                "+2 dB",
                "+1 dB",
                " 0 dB",
                "-1 dB",
                "-2 dB",
                "-3 dB",
                "-4 dB",
                "-5 dB",
                "-6 dB",
                "-7 dB",
                "-8 dB",
                "-9 dB",
                "-10 dB",
                "-11 dB",
                "-12 dB",
                "-13 dB",
                "-14 dB",
                "-15 dB",
                "-16 dB",
                "-17 dB",
                "-18 dB",
                "-24 dB",
                "-27 dB",
                "-30 dB",
                "-36 dB",
                "-42 dB"
              ]
            }
          }
        },
        "errors": []
      },
      "durationMs": 16,
      "error": null
    }
  },
  {
    "id": "EVT-0080",
    "timestamp": "2026-02-01T10:42:40.955Z",
    "relativeMs": 3736,
    "type": "action-end",
    "origin": "system",
    "correlationId": "COR-0021",
    "data": {
      "status": "success",
      "error": null
    }
  },
  {
    "id": "EVT-0081",
    "timestamp": "2026-02-01T10:42:41.068Z",
    "relativeMs": 3849,
    "type": "action-start",
    "origin": "user",
    "correlationId": "COR-0022",
    "data": {
      "name": "click Refresh",
      "component": "GlobalInteraction",
      "context": {
        "ui": {
          "route": "/config",
          "query": ""
        },
        "platform": "web",
        "featureFlags": {
          "hvsc_enabled": true
        },
        "playback": {
          "queueLength": 0,
          "currentIndex": -1,
          "currentItemId": null,
          "isPlaying": false,
          "elapsedMs": 0,
          "durationMs": null
        },
        "device": {
          "deviceId": null,
          "connectionState": "READY"
        }
      }
    }
  },
  {
    "id": "EVT-0082",
    "timestamp": "2026-02-01T10:42:41.069Z",
    "relativeMs": 3850,
    "type": "action-end",
    "origin": "user",
    "correlationId": "COR-0022",
    "data": {
      "status": "success",
      "error": null
    }
  },
  {
    "id": "EVT-0083",
    "timestamp": "2026-02-01T10:42:41.071Z",
    "relativeMs": 3852,
    "type": "action-start",
    "origin": "user",
    "correlationId": "COR-0023",
    "data": {
      "name": "click Refresh",
      "component": "Button",
      "context": {
        "ui": {
          "route": "/config",
          "query": ""
        },
        "platform": "web",
        "featureFlags": {
          "hvsc_enabled": true
        },
        "playback": {
          "queueLength": 0,
          "currentIndex": -1,
          "currentItemId": null,
          "isPlaying": false,
          "elapsedMs": 0,
          "durationMs": null
        },
        "device": {
          "deviceId": null,
          "connectionState": "READY"
        }
      }
    }
  },
  {
    "id": "EVT-0084",
    "timestamp": "2026-02-01T10:42:41.072Z",
    "relativeMs": 3853,
    "type": "action-start",
    "origin": "system",
    "correlationId": "COR-0024",
    "data": {
      "name": "rest.get",
      "component": null,
      "context": {
        "ui": {
          "route": "/config",
          "query": ""
        },
        "platform": "web",
        "featureFlags": {
          "hvsc_enabled": true
        },
        "playback": {
          "queueLength": 0,
          "currentIndex": -1,
          "currentItemId": null,
          "isPlaying": false,
          "elapsedMs": 0,
          "durationMs": null
        },
        "device": {
          "deviceId": null,
          "connectionState": "READY"
        }
      }
    }
  },
  {
    "id": "EVT-0085",
    "timestamp": "2026-02-01T10:42:41.072Z",
    "relativeMs": 3853,
    "type": "backend-decision",
    "origin": "automatic",
    "correlationId": "COR-0024",
    "data": {
      "selectedTarget": "external-mock",
      "reason": "test-mode"
    }
  },
  {
    "id": "EVT-0086",
    "timestamp": "2026-02-01T10:42:41.073Z",
    "relativeMs": 3854,
    "type": "rest-request",
    "origin": "system",
    "correlationId": "COR-0024",
    "data": {
      "method": "GET",
      "url": "http://127.0.0.1:41889/v1/configs/U64%20Specific%20Settings",
      "normalizedUrl": "/v1/configs/U64%20Specific%20Settings",
      "headers": {
        "Content-Type": "application/json",
        "X-C64U-Host": "127.0.0.1:41889"
      },
      "body": null,
      "target": "external-mock"
    }
  },
  {
    "id": "EVT-0087",
    "timestamp": "2026-02-01T10:42:41.092Z",
    "relativeMs": 3873,
    "type": "rest-response",
    "origin": "system",
    "correlationId": "COR-0024",
    "data": {
      "status": 200,
      "body": {
        "U64 Specific Settings": {
          "items": {
            "System Mode": {
              "selected": "NTSC",
              "options": [
                "PAL",
                "NTSC",
                "PAL-60",
                "NTSC-50",
                "PAL-60/L",
                "NTSC-50/L"
              ]
            },
            "Digital Video Mode": {
              "selected": "Auto",
              "options": [
                "Auto",
                "HDMI",
                "DVI"
              ]
            },
            "HDMI Scan lines": {
              "selected": "Disabled",
              "options": [
                "Disabled",
                "Enabled"
              ]
            }
          }
        },
        "errors": []
      },
      "durationMs": 8,
      "error": null
    }
  },
  {
    "id": "EVT-0088",
    "timestamp": "2026-02-01T10:42:41.093Z",
    "relativeMs": 3874,
    "type": "action-end",
    "origin": "system",
    "correlationId": "COR-0024",
    "data": {
      "status": "success",
      "error": null
    }
  },
  {
    "id": "EVT-0089",
    "timestamp": "2026-02-01T10:42:41.094Z",
    "relativeMs": 3875,
    "type": "action-end",
    "origin": "user",
    "correlationId": "COR-0023",
    "data": {
      "status": "success",
      "error": null
    }
  },
  {
    "id": "EVT-0090",
    "timestamp": "2026-02-01T10:42:41.881Z",
    "relativeMs": 4662,
    "type": "action-start",
    "origin": "user",
    "correlationId": "COR-0025",
    "data": {
      "name": "click U64 Specific Settings",
      "component": "GlobalInteraction",
      "context": {
        "ui": {
          "route": "/config",
          "query": ""
        },
        "platform": "web",
        "featureFlags": {
          "hvsc_enabled": true
        },
        "playback": {
          "queueLength": 0,
          "currentIndex": -1,
          "currentItemId": null,
          "isPlaying": false,
          "elapsedMs": 0,
          "durationMs": null
        },
        "device": {
          "deviceId": null,
          "connectionState": "READY"
        }
      }
    }
  },
  {
    "id": "EVT-0091",
    "timestamp": "2026-02-01T10:42:41.883Z",
    "relativeMs": 4664,
    "type": "action-end",
    "origin": "user",
    "correlationId": "COR-0025",
    "data": {
      "status": "success",
      "error": null
    }
  },
  {
    "id": "EVT-0092",
    "timestamp": "2026-02-01T10:42:41.884Z",
    "relativeMs": 4665,
    "type": "action-start",
    "origin": "user",
    "correlationId": "COR-0026",
    "data": {
      "name": "toggle U64 Specific Settings",
      "component": "ConfigSection",
      "context": {
        "ui": {
          "route": "/config",
          "query": ""
        },
        "platform": "web",
        "featureFlags": {
          "hvsc_enabled": true
        },
        "playback": {
          "queueLength": 0,
          "currentIndex": -1,
          "currentItemId": null,
          "isPlaying": false,
          "elapsedMs": 0,
          "durationMs": null
        },
        "device": {
          "deviceId": null,
          "connectionState": "READY"
        }
      }
    }
  },
  {
    "id": "EVT-0093",
    "timestamp": "2026-02-01T10:42:41.886Z",
    "relativeMs": 4667,
    "type": "action-end",
    "origin": "user",
    "correlationId": "COR-0026",
    "data": {
      "status": "success",
      "error": null
    }
  }
]