[
  {
    "id": "EVT-0000",
    "timestamp": "2026-02-01T17:21:47.888Z",
    "relativeMs": 230,
    "type": "action-start",
    "origin": "system",
    "correlationId": "COR-0000",
    "data": {
      "name": "rest.get",
      "component": null,
      "context": {
        "ui": {
          "route": "/config",
          "query": ""
        },
        "platform": "web",
        "featureFlags": {
          "hvsc_enabled": true
        },
        "playback": {
          "queueLength": 0,
          "currentIndex": -1,
          "currentItemId": null,
          "isPlaying": false,
          "elapsedMs": 0,
          "durationMs": null
        },
        "device": {
          "deviceId": null,
          "connectionState": "UNKNOWN"
        }
      }
    }
  },
  {
    "id": "EVT-0001",
    "timestamp": "2026-02-01T17:21:47.890Z",
    "relativeMs": 232,
    "type": "device-guard",
    "origin": "system",
    "correlationId": "COR-0000",
    "data": {
      "decision": "block",
      "reason": "state",
      "state": "UNKNOWN"
    }
  },
  {
    "id": "EVT-0002",
    "timestamp": "2026-02-01T17:21:47.903Z",
    "relativeMs": 245,
    "type": "action-start",
    "origin": "system",
    "correlationId": "COR-0001",
    "data": {
      "name": "rest.get",
      "component": null,
      "context": {
        "ui": {
          "route": "/config",
          "query": ""
        },
        "platform": "web",
        "featureFlags": {
          "hvsc_enabled": true
        },
        "playback": {
          "queueLength": 0,
          "currentIndex": -1,
          "currentItemId": null,
          "isPlaying": false,
          "elapsedMs": 0,
          "durationMs": null
        },
        "device": {
          "deviceId": null,
          "connectionState": "UNKNOWN"
        }
      }
    }
  },
  {
    "id": "EVT-0003",
    "timestamp": "2026-02-01T17:21:47.904Z",
    "relativeMs": 246,
    "type": "device-guard",
    "origin": "system",
    "correlationId": "COR-0001",
    "data": {
      "decision": "block",
      "reason": "state",
      "state": "UNKNOWN"
    }
  },
  {
    "id": "EVT-0004",
    "timestamp": "2026-02-01T17:21:47.904Z",
    "relativeMs": 246,
    "type": "error",
    "origin": "system",
    "correlationId": "COR-0000",
    "data": {
      "message": "Device not ready for requests",
      "name": "Error"
    }
  },
  {
    "id": "EVT-0005",
    "timestamp": "2026-02-01T17:21:47.904Z",
    "relativeMs": 246,
    "type": "action-end",
    "origin": "system",
    "correlationId": "COR-0000",
    "data": {
      "status": "error",
      "error": "Device not ready for requests"
    }
  },
  {
    "id": "EVT-0006",
    "timestamp": "2026-02-01T17:21:47.905Z",
    "relativeMs": 247,
    "type": "error",
    "origin": "system",
    "correlationId": "COR-0001",
    "data": {
      "message": "Device not ready for requests",
      "name": "Error"
    }
  },
  {
    "id": "EVT-0007",
    "timestamp": "2026-02-01T17:21:47.905Z",
    "relativeMs": 247,
    "type": "action-end",
    "origin": "system",
    "correlationId": "COR-0001",
    "data": {
      "status": "error",
      "error": "Device not ready for requests"
    }
  },
  {
    "id": "EVT-0008",
    "timestamp": "2026-02-01T17:21:47.907Z",
    "relativeMs": 249,
    "type": "action-start",
    "origin": "system",
    "correlationId": "COR-0002",
    "data": {
      "name": "rest.get",
      "component": null,
      "context": {
        "ui": {
          "route": "/config",
          "query": ""
        },
        "platform": "web",
        "featureFlags": {
          "hvsc_enabled": true
        },
        "playback": {
          "queueLength": 0,
          "currentIndex": -1,
          "currentItemId": null,
          "isPlaying": false,
          "elapsedMs": 0,
          "durationMs": null
        },
        "device": {
          "deviceId": null,
          "connectionState": "DISCOVERING"
        }
      }
    }
  },
  {
    "id": "EVT-0009",
    "timestamp": "2026-02-01T17:21:47.908Z",
    "relativeMs": 250,
    "type": "backend-decision",
    "origin": "system",
    "correlationId": "COR-0002",
    "data": {
      "selectedTarget": "real-device",
      "reason": "reachable"
    }
  },
  {
    "id": "EVT-0010",
    "timestamp": "2026-02-01T17:21:47.908Z",
    "relativeMs": 250,
    "type": "rest-request",
    "origin": "system",
    "correlationId": "COR-0002",
    "data": {
      "method": "GET",
      "url": "http://127.0.0.1:37419/v1/info",
      "normalizedUrl": "/v1/info",
      "headers": {
        "Content-Type": "application/json",
        "X-C64U-Host": "127.0.0.1:37419"
      },
      "body": null,
      "target": "real-device"
    }
  },
  {
    "id": "EVT-0011",
    "timestamp": "2026-02-01T17:21:48.065Z",
    "relativeMs": 407,
    "type": "rest-response",
    "origin": "system",
    "correlationId": "COR-0002",
    "data": {
      "status": 503,
      "body": {
        "errors": [
          "Device unreachable"
        ]
      },
      "durationMs": 110,
      "error": "HTTP 503: Service Unavailable"
    }
  },
  {
    "id": "EVT-0012",
    "timestamp": "2026-02-01T17:21:48.065Z",
    "relativeMs": 407,
    "type": "error",
    "origin": "system",
    "correlationId": "COR-0002",
    "data": {
      "message": "HTTP 503: Service Unavailable",
      "name": "Error"
    }
  },
  {
    "id": "EVT-0013",
    "timestamp": "2026-02-01T17:21:48.067Z",
    "relativeMs": 409,
    "type": "action-end",
    "origin": "system",
    "correlationId": "COR-0002",
    "data": {
      "status": "error",
      "error": "HTTP 503: Service Unavailable"
    }
  },
  {
    "id": "EVT-0014",
    "timestamp": "2026-02-01T17:21:48.509Z",
    "relativeMs": 851,
    "type": "action-start",
    "origin": "system",
    "correlationId": "COR-0003",
    "data": {
      "name": "rest.get",
      "component": null,
      "context": {
        "ui": {
          "route": "/config",
          "query": ""
        },
        "platform": "web",
        "featureFlags": {
          "hvsc_enabled": true
        },
        "playback": {
          "queueLength": 0,
          "currentIndex": -1,
          "currentItemId": null,
          "isPlaying": false,
          "elapsedMs": 0,
          "durationMs": null
        },
        "device": {
          "deviceId": null,
          "connectionState": "DISCOVERING"
        }
      }
    }
  },
  {
    "id": "EVT-0015",
    "timestamp": "2026-02-01T17:21:48.509Z",
    "relativeMs": 851,
    "type": "backend-decision",
    "origin": "system",
    "correlationId": "COR-0003",
    "data": {
      "selectedTarget": "real-device",
      "reason": "reachable"
    }
  },
  {
    "id": "EVT-0016",
    "timestamp": "2026-02-01T17:21:48.509Z",
    "relativeMs": 851,
    "type": "rest-request",
    "origin": "system",
    "correlationId": "COR-0003",
    "data": {
      "method": "GET",
      "url": "http://127.0.0.1:37419/v1/info",
      "normalizedUrl": "/v1/info",
      "headers": {
        "Content-Type": "application/json",
        "X-C64U-Host": "127.0.0.1:37419"
      },
      "body": null,
      "target": "real-device"
    }
  },
  {
    "id": "EVT-0017",
    "timestamp": "2026-02-01T17:21:48.554Z",
    "relativeMs": 896,
    "type": "rest-response",
    "origin": "system",
    "correlationId": "COR-0003",
    "data": {
      "status": 503,
      "body": {
        "errors": [
          "Device unreachable"
        ]
      },
      "durationMs": 43,
      "error": "HTTP 503: Service Unavailable"
    }
  },
  {
    "id": "EVT-0018",
    "timestamp": "2026-02-01T17:21:48.554Z",
    "relativeMs": 896,
    "type": "error",
    "origin": "system",
    "correlationId": "COR-0003",
    "data": {
      "message": "HTTP 503: Service Unavailable",
      "name": "Error"
    }
  },
  {
    "id": "EVT-0019",
    "timestamp": "2026-02-01T17:21:48.555Z",
    "relativeMs": 897,
    "type": "action-end",
    "origin": "system",
    "correlationId": "COR-0003",
    "data": {
      "status": "error",
      "error": "HTTP 503: Service Unavailable"
    }
  },
  {
    "id": "EVT-0020",
    "timestamp": "2026-02-01T17:21:48.916Z",
    "relativeMs": 1258,
    "type": "action-start",
    "origin": "system",
    "correlationId": "COR-0004",
    "data": {
      "name": "rest.get",
      "component": null,
      "context": {
        "ui": {
          "route": "/config",
          "query": ""
        },
        "platform": "web",
        "featureFlags": {
          "hvsc_enabled": true
        },
        "playback": {
          "queueLength": 0,
          "currentIndex": -1,
          "currentItemId": null,
          "isPlaying": false,
          "elapsedMs": 0,
          "durationMs": null
        },
        "device": {
          "deviceId": null,
          "connectionState": "DISCOVERING"
        }
      }
    }
  },
  {
    "id": "EVT-0021",
    "timestamp": "2026-02-01T17:21:48.916Z",
    "relativeMs": 1258,
    "type": "device-guard",
    "origin": "system",
    "correlationId": "COR-0004",
    "data": {
      "decision": "block",
      "reason": "state",
      "state": "DISCOVERING"
    }
  },
  {
    "id": "EVT-0022",
    "timestamp": "2026-02-01T17:21:48.916Z",
    "relativeMs": 1258,
    "type": "error",
    "origin": "system",
    "correlationId": "COR-0004",
    "data": {
      "message": "Device not ready for requests",
      "name": "Error"
    }
  },
  {
    "id": "EVT-0023",
    "timestamp": "2026-02-01T17:21:48.916Z",
    "relativeMs": 1258,
    "type": "action-end",
    "origin": "system",
    "correlationId": "COR-0004",
    "data": {
      "status": "error",
      "error": "Device not ready for requests"
    }
  },
  {
    "id": "EVT-0024",
    "timestamp": "2026-02-01T17:21:49.013Z",
    "relativeMs": 1355,
    "type": "action-start",
    "origin": "system",
    "correlationId": "COR-0005",
    "data": {
      "name": "rest.get",
      "component": null,
      "context": {
        "ui": {
          "route": "/config",
          "query": ""
        },
        "platform": "web",
        "featureFlags": {
          "hvsc_enabled": true
        },
        "playback": {
          "queueLength": 0,
          "currentIndex": -1,
          "currentItemId": null,
          "isPlaying": false,
          "elapsedMs": 0,
          "durationMs": null
        },
        "device": {
          "deviceId": null,
          "connectionState": "CONNECTING"
        }
      }
    }
  },
  {
    "id": "EVT-0025",
    "timestamp": "2026-02-01T17:21:49.013Z",
    "relativeMs": 1355,
    "type": "action-start",
    "origin": "system",
    "correlationId": "COR-0006",
    "data": {
      "name": "rest.get",
      "component": null,
      "context": {
        "ui": {
          "route": "/config",
          "query": ""
        },
        "platform": "web",
        "featureFlags": {
          "hvsc_enabled": true
        },
        "playback": {
          "queueLength": 0,
          "currentIndex": -1,
          "currentItemId": null,
          "isPlaying": false,
          "elapsedMs": 0,
          "durationMs": null
        },
        "device": {
          "deviceId": null,
          "connectionState": "CONNECTING"
        }
      }
    }
  },
  {
    "id": "EVT-0026",
    "timestamp": "2026-02-01T17:21:49.018Z",
    "relativeMs": 1360,
    "type": "backend-decision",
    "origin": "system",
    "correlationId": "COR-0005",
    "data": {
      "selectedTarget": "internal-mock",
      "reason": "demo-mode"
    }
  },
  {
    "id": "EVT-0027",
    "timestamp": "2026-02-01T17:21:49.018Z",
    "relativeMs": 1360,
    "type": "rest-request",
    "origin": "system",
    "correlationId": "COR-0005",
    "data": {
      "method": "GET",
      "url": "http://127.0.0.1:36943/v1/configs",
      "normalizedUrl": "/v1/configs",
      "headers": {
        "Content-Type": "application/json",
        "X-C64U-Host": "127.0.0.1:36943"
      },
      "body": null,
      "target": "internal-mock"
    }
  },
  {
    "id": "EVT-0028",
    "timestamp": "2026-02-01T17:21:49.046Z",
    "relativeMs": 1388,
    "type": "rest-response",
    "origin": "system",
    "correlationId": "COR-0005",
    "data": {
      "status": 200,
      "body": {
        "categories": [
          "U64 Specific Settings",
          "Audio Mixer",
          "UltiSID Configuration",
          "Drive A Settings",
          "Drive B Settings"
        ],
        "errors": []
      },
      "durationMs": 23,
      "error": null
    }
  },
  {
    "id": "EVT-0029",
    "timestamp": "2026-02-01T17:21:49.046Z",
    "relativeMs": 1388,
    "type": "action-end",
    "origin": "system",
    "correlationId": "COR-0005",
    "data": {
      "status": "success",
      "error": null
    }
  },
  {
    "id": "EVT-0030",
    "timestamp": "2026-02-01T17:21:49.046Z",
    "relativeMs": 1388,
    "type": "backend-decision",
    "origin": "system",
    "correlationId": "COR-0006",
    "data": {
      "selectedTarget": "internal-mock",
      "reason": "demo-mode"
    }
  },
  {
    "id": "EVT-0031",
    "timestamp": "2026-02-01T17:21:49.046Z",
    "relativeMs": 1388,
    "type": "rest-request",
    "origin": "system",
    "correlationId": "COR-0006",
    "data": {
      "method": "GET",
      "url": "http://127.0.0.1:36943/v1/info",
      "normalizedUrl": "/v1/info",
      "headers": {
        "Content-Type": "application/json",
        "X-C64U-Host": "127.0.0.1:36943"
      },
      "body": null,
      "target": "internal-mock"
    }
  },
  {
    "id": "EVT-0032",
    "timestamp": "2026-02-01T17:21:49.256Z",
    "relativeMs": 1598,
    "type": "rest-response",
    "origin": "system",
    "correlationId": "COR-0006",
    "data": {
      "status": 200,
      "body": {
        "product": "C64 Ultimate",
        "firmware_version": "3.12.0",
        "fpga_version": "1.0.0",
        "core_version": "1.0.0",
        "hostname": "c64u",
        "unique_id": "TEST-123",
        "errors": []
      },
      "durationMs": 162,
      "error": null
    }
  },
  {
    "id": "EVT-0033",
    "timestamp": "2026-02-01T17:21:49.256Z",
    "relativeMs": 1598,
    "type": "action-end",
    "origin": "system",
    "correlationId": "COR-0006",
    "data": {
      "status": "success",
      "error": null
    }
  },
  {
    "id": "EVT-0034",
    "timestamp": "2026-02-01T17:21:49.932Z",
    "relativeMs": 2274,
    "type": "action-start",
    "origin": "system",
    "correlationId": "COR-0007",
    "data": {
      "name": "rest.get",
      "component": null,
      "context": {
        "ui": {
          "route": "/settings",
          "query": ""
        },
        "platform": "web",
        "featureFlags": {
          "hvsc_enabled": true
        },
        "playback": {
          "queueLength": 0,
          "currentIndex": -1,
          "currentItemId": null,
          "isPlaying": false,
          "elapsedMs": 0,
          "durationMs": null
        },
        "device": {
          "deviceId": null,
          "connectionState": "UNKNOWN"
        }
      }
    }
  },
  {
    "id": "EVT-0035",
    "timestamp": "2026-02-01T17:21:49.932Z",
    "relativeMs": 2274,
    "type": "device-guard",
    "origin": "system",
    "correlationId": "COR-0007",
    "data": {
      "decision": "block",
      "reason": "state",
      "state": "UNKNOWN"
    }
  },
  {
    "id": "EVT-0036",
    "timestamp": "2026-02-01T17:21:49.936Z",
    "relativeMs": 2278,
    "type": "error",
    "origin": "system",
    "correlationId": "COR-0007",
    "data": {
      "message": "Device not ready for requests",
      "name": "Error"
    }
  },
  {
    "id": "EVT-0037",
    "timestamp": "2026-02-01T17:21:49.936Z",
    "relativeMs": 2278,
    "type": "action-end",
    "origin": "system",
    "correlationId": "COR-0007",
    "data": {
      "status": "error",
      "error": "Device not ready for requests"
    }
  },
  {
    "id": "EVT-0038",
    "timestamp": "2026-02-01T17:21:49.936Z",
    "relativeMs": 2278,
    "type": "action-start",
    "origin": "system",
    "correlationId": "COR-0008",
    "data": {
      "name": "rest.get",
      "component": null,
      "context": {
        "ui": {
          "route": "/settings",
          "query": ""
        },
        "platform": "web",
        "featureFlags": {
          "hvsc_enabled": true
        },
        "playback": {
          "queueLength": 0,
          "currentIndex": -1,
          "currentItemId": null,
          "isPlaying": false,
          "elapsedMs": 0,
          "durationMs": null
        },
        "device": {
          "deviceId": null,
          "connectionState": "DISCOVERING"
        }
      }
    }
  },
  {
    "id": "EVT-0039",
    "timestamp": "2026-02-01T17:21:49.937Z",
    "relativeMs": 2279,
    "type": "backend-decision",
    "origin": "system",
    "correlationId": "COR-0008",
    "data": {
      "selectedTarget": "real-device",
      "reason": "reachable"
    }
  },
  {
    "id": "EVT-0040",
    "timestamp": "2026-02-01T17:21:49.937Z",
    "relativeMs": 2279,
    "type": "rest-request",
    "origin": "system",
    "correlationId": "COR-0008",
    "data": {
      "method": "GET",
      "url": "http://127.0.0.1:37419/v1/info",
      "normalizedUrl": "/v1/info",
      "headers": {
        "Content-Type": "application/json",
        "X-C64U-Host": "127.0.0.1:37419"
      },
      "body": null,
      "target": "real-device"
    }
  },
  {
    "id": "EVT-0041",
    "timestamp": "2026-02-01T17:21:50.291Z",
    "relativeMs": 2633,
    "type": "rest-response",
    "origin": "system",
    "correlationId": "COR-0008",
    "data": {
      "status": 200,
      "body": {
        "product": "C64 Ultimate",
        "firmware_version": "3.12.0",
        "fpga_version": "1.0.0",
        "core_version": "1.0.0",
        "hostname": "c64u",
        "unique_id": "TEST-123",
        "errors": []
      },
      "durationMs": 264,
      "error": null
    }
  },
  {
    "id": "EVT-0042",
    "timestamp": "2026-02-01T17:21:50.291Z",
    "relativeMs": 2633,
    "type": "action-end",
    "origin": "system",
    "correlationId": "COR-0008",
    "data": {
      "status": "success",
      "error": null
    }
  },
  {
    "id": "EVT-0043",
    "timestamp": "2026-02-01T17:21:50.612Z",
    "relativeMs": 2954,
    "type": "action-start",
    "origin": "user",
    "correlationId": "COR-0009",
    "data": {
      "name": "click Save & Connect",
      "component": "GlobalInteraction",
      "context": {
        "ui": {
          "route": "/settings",
          "query": ""
        },
        "platform": "web",
        "featureFlags": {
          "hvsc_enabled": true
        },
        "playback": {
          "queueLength": 0,
          "currentIndex": -1,
          "currentItemId": null,
          "isPlaying": false,
          "elapsedMs": 0,
          "durationMs": null
        },
        "device": {
          "deviceId": null,
          "connectionState": "REAL_CONNECTED"
        }
      }
    }
  },
  {
    "id": "EVT-0044",
    "timestamp": "2026-02-01T17:21:50.614Z",
    "relativeMs": 2956,
    "type": "action-end",
    "origin": "user",
    "correlationId": "COR-0009",
    "data": {
      "status": "success",
      "error": null
    }
  },
  {
    "id": "EVT-0045",
    "timestamp": "2026-02-01T17:21:50.614Z",
    "relativeMs": 2956,
    "type": "action-start",
    "origin": "user",
    "correlationId": "COR-0010",
    "data": {
      "name": "click Save & Connect",
      "component": "Button",
      "context": {
        "ui": {
          "route": "/settings",
          "query": ""
        },
        "platform": "web",
        "featureFlags": {
          "hvsc_enabled": true
        },
        "playback": {
          "queueLength": 0,
          "currentIndex": -1,
          "currentItemId": null,
          "isPlaying": false,
          "elapsedMs": 0,
          "durationMs": null
        },
        "device": {
          "deviceId": null,
          "connectionState": "REAL_CONNECTED"
        }
      }
    }
  },
  {
    "id": "EVT-0046",
    "timestamp": "2026-02-01T17:21:50.614Z",
    "relativeMs": 2956,
    "type": "action-start",
    "origin": "user",
    "correlationId": "COR-0011",
    "data": {
      "name": "SettingsPage.anonymousAction",
      "component": "SettingsPage",
      "context": {
        "ui": {
          "route": "/settings",
          "query": ""
        },
        "platform": "web",
        "featureFlags": {
          "hvsc_enabled": true
        },
        "playback": {
          "queueLength": 0,
          "currentIndex": -1,
          "currentItemId": null,
          "isPlaying": false,
          "elapsedMs": 0,
          "durationMs": null
        },
        "device": {
          "deviceId": null,
          "connectionState": "REAL_CONNECTED"
        }
      }
    }
  },
  {
    "id": "EVT-0047",
    "timestamp": "2026-02-01T17:21:50.615Z",
    "relativeMs": 2957,
    "type": "action-start",
    "origin": "system",
    "correlationId": "COR-0012",
    "data": {
      "name": "rest.get",
      "component": null,
      "context": {
        "ui": {
          "route": "/settings",
          "query": ""
        },
        "platform": "web",
        "featureFlags": {
          "hvsc_enabled": true
        },
        "playback": {
          "queueLength": 0,
          "currentIndex": -1,
          "currentItemId": null,
          "isPlaying": false,
          "elapsedMs": 0,
          "durationMs": null
        },
        "device": {
          "deviceId": null,
          "connectionState": "DISCOVERING"
        }
      }
    }
  },
  {
    "id": "EVT-0048",
    "timestamp": "2026-02-01T17:21:50.615Z",
    "relativeMs": 2957,
    "type": "backend-decision",
    "origin": "system",
    "correlationId": "COR-0012",
    "data": {
      "selectedTarget": "real-device",
      "reason": "reachable"
    }
  },
  {
    "id": "EVT-0049",
    "timestamp": "2026-02-01T17:21:50.615Z",
    "relativeMs": 2957,
    "type": "rest-request",
    "origin": "system",
    "correlationId": "COR-0012",
    "data": {
      "method": "GET",
      "url": "http://127.0.0.1:37419/v1/info",
      "normalizedUrl": "/v1/info",
      "headers": {
        "Content-Type": "application/json",
        "X-C64U-Host": "127.0.0.1:37419"
      },
      "body": null,
      "target": "real-device"
    }
  },
  {
    "id": "EVT-0050",
    "timestamp": "2026-02-01T17:21:50.680Z",
    "relativeMs": 3022,
    "type": "action-end",
    "origin": "user",
    "correlationId": "COR-0011",
    "data": {
      "status": "success",
      "error": null
    }
  },
  {
    "id": "EVT-0051",
    "timestamp": "2026-02-01T17:21:50.680Z",
    "relativeMs": 3022,
    "type": "action-end",
    "origin": "user",
    "correlationId": "COR-0010",
    "data": {
      "status": "success",
      "error": null
    }
  },
  {
    "id": "EVT-0052",
    "timestamp": "2026-02-01T17:21:50.796Z",
    "relativeMs": 3138,
    "type": "rest-response",
    "origin": "system",
    "correlationId": "COR-0012",
    "data": {
      "status": 200,
      "body": {
        "product": "C64 Ultimate",
        "firmware_version": "3.12.0",
        "fpga_version": "1.0.0",
        "core_version": "1.0.0",
        "hostname": "c64u",
        "unique_id": "TEST-123",
        "errors": []
      },
      "durationMs": 154,
      "error": null
    }
  },
  {
    "id": "EVT-0053",
    "timestamp": "2026-02-01T17:21:50.796Z",
    "relativeMs": 3138,
    "type": "action-end",
    "origin": "system",
    "correlationId": "COR-0012",
    "data": {
      "status": "success",
      "error": null
    }
  },
  {
    "id": "EVT-0054",
    "timestamp": "2026-02-01T17:21:51.068Z",
    "relativeMs": 3410,
    "type": "action-start",
    "origin": "system",
    "correlationId": "COR-0013",
    "data": {
      "name": "rest.get",
      "component": null,
      "context": {
        "ui": {
          "route": "/config",
          "query": ""
        },
        "platform": "web",
        "featureFlags": {
          "hvsc_enabled": true
        },
        "playback": {
          "queueLength": 0,
          "currentIndex": -1,
          "currentItemId": null,
          "isPlaying": false,
          "elapsedMs": 0,
          "durationMs": null
        },
        "device": {
          "deviceId": null,
          "connectionState": "UNKNOWN"
        }
      }
    }
  },
  {
    "id": "EVT-0055",
    "timestamp": "2026-02-01T17:21:51.069Z",
    "relativeMs": 3411,
    "type": "device-guard",
    "origin": "system",
    "correlationId": "COR-0013",
    "data": {
      "decision": "block",
      "reason": "state",
      "state": "UNKNOWN"
    }
  },
  {
    "id": "EVT-0056",
    "timestamp": "2026-02-01T17:21:51.090Z",
    "relativeMs": 3432,
    "type": "action-start",
    "origin": "system",
    "correlationId": "COR-0014",
    "data": {
      "name": "rest.get",
      "component": null,
      "context": {
        "ui": {
          "route": "/config",
          "query": ""
        },
        "platform": "web",
        "featureFlags": {
          "hvsc_enabled": true
        },
        "playback": {
          "queueLength": 0,
          "currentIndex": -1,
          "currentItemId": null,
          "isPlaying": false,
          "elapsedMs": 0,
          "durationMs": null
        },
        "device": {
          "deviceId": null,
          "connectionState": "UNKNOWN"
        }
      }
    }
  },
  {
    "id": "EVT-0057",
    "timestamp": "2026-02-01T17:21:51.090Z",
    "relativeMs": 3432,
    "type": "device-guard",
    "origin": "system",
    "correlationId": "COR-0014",
    "data": {
      "decision": "block",
      "reason": "state",
      "state": "UNKNOWN"
    }
  },
  {
    "id": "EVT-0058",
    "timestamp": "2026-02-01T17:21:51.090Z",
    "relativeMs": 3432,
    "type": "error",
    "origin": "system",
    "correlationId": "COR-0013",
    "data": {
      "message": "Device not ready for requests",
      "name": "Error"
    }
  },
  {
    "id": "EVT-0059",
    "timestamp": "2026-02-01T17:21:51.090Z",
    "relativeMs": 3432,
    "type": "action-end",
    "origin": "system",
    "correlationId": "COR-0013",
    "data": {
      "status": "error",
      "error": "Device not ready for requests"
    }
  },
  {
    "id": "EVT-0060",
    "timestamp": "2026-02-01T17:21:51.091Z",
    "relativeMs": 3433,
    "type": "error",
    "origin": "system",
    "correlationId": "COR-0014",
    "data": {
      "message": "Device not ready for requests",
      "name": "Error"
    }
  },
  {
    "id": "EVT-0061",
    "timestamp": "2026-02-01T17:21:51.091Z",
    "relativeMs": 3433,
    "type": "action-end",
    "origin": "system",
    "correlationId": "COR-0014",
    "data": {
      "status": "error",
      "error": "Device not ready for requests"
    }
  },
  {
    "id": "EVT-0062",
    "timestamp": "2026-02-01T17:21:51.091Z",
    "relativeMs": 3433,
    "type": "action-start",
    "origin": "system",
    "correlationId": "COR-0015",
    "data": {
      "name": "rest.get",
      "component": null,
      "context": {
        "ui": {
          "route": "/config",
          "query": ""
        },
        "platform": "web",
        "featureFlags": {
          "hvsc_enabled": true
        },
        "playback": {
          "queueLength": 0,
          "currentIndex": -1,
          "currentItemId": null,
          "isPlaying": false,
          "elapsedMs": 0,
          "durationMs": null
        },
        "device": {
          "deviceId": null,
          "connectionState": "DISCOVERING"
        }
      }
    }
  },
  {
    "id": "EVT-0063",
    "timestamp": "2026-02-01T17:21:51.091Z",
    "relativeMs": 3433,
    "type": "backend-decision",
    "origin": "system",
    "correlationId": "COR-0015",
    "data": {
      "selectedTarget": "real-device",
      "reason": "reachable"
    }
  },
  {
    "id": "EVT-0064",
    "timestamp": "2026-02-01T17:21:51.091Z",
    "relativeMs": 3433,
    "type": "rest-request",
    "origin": "system",
    "correlationId": "COR-0015",
    "data": {
      "method": "GET",
      "url": "http://127.0.0.1:37419/v1/info",
      "normalizedUrl": "/v1/info",
      "headers": {
        "Content-Type": "application/json",
        "X-C64U-Host": "127.0.0.1:37419"
      },
      "body": null,
      "target": "real-device"
    }
  },
  {
    "id": "EVT-0065",
    "timestamp": "2026-02-01T17:21:51.241Z",
    "relativeMs": 3583,
    "type": "rest-response",
    "origin": "system",
    "correlationId": "COR-0015",
    "data": {
      "status": 200,
      "body": {
        "product": "C64 Ultimate",
        "firmware_version": "3.12.0",
        "fpga_version": "1.0.0",
        "core_version": "1.0.0",
        "hostname": "c64u",
        "unique_id": "TEST-123",
        "errors": []
      },
      "durationMs": 121,
      "error": null
    }
  },
  {
    "id": "EVT-0066",
    "timestamp": "2026-02-01T17:21:51.244Z",
    "relativeMs": 3586,
    "type": "action-end",
    "origin": "system",
    "correlationId": "COR-0015",
    "data": {
      "status": "success",
      "error": null
    }
  },
  {
    "id": "EVT-0067",
    "timestamp": "2026-02-01T17:21:52.103Z",
    "relativeMs": 4445,
    "type": "action-start",
    "origin": "system",
    "correlationId": "COR-0016",
    "data": {
      "name": "rest.get",
      "component": null,
      "context": {
        "ui": {
          "route": "/config",
          "query": ""
        },
        "platform": "web",
        "featureFlags": {
          "hvsc_enabled": true
        },
        "playback": {
          "queueLength": 0,
          "currentIndex": -1,
          "currentItemId": null,
          "isPlaying": false,
          "elapsedMs": 0,
          "durationMs": null
        },
        "device": {
          "deviceId": null,
          "connectionState": "REAL_CONNECTED"
        }
      }
    }
  },
  {
    "id": "EVT-0068",
    "timestamp": "2026-02-01T17:21:52.103Z",
    "relativeMs": 4445,
    "type": "backend-decision",
    "origin": "system",
    "correlationId": "COR-0016",
    "data": {
      "selectedTarget": "real-device",
      "reason": "reachable"
    }
  },
  {
    "id": "EVT-0069",
    "timestamp": "2026-02-01T17:21:52.103Z",
    "relativeMs": 4445,
    "type": "rest-request",
    "origin": "system",
    "correlationId": "COR-0016",
    "data": {
      "method": "GET",
      "url": "http://127.0.0.1:37419/v1/configs",
      "normalizedUrl": "/v1/configs",
      "headers": {
        "Content-Type": "application/json",
        "X-C64U-Host": "127.0.0.1:37419"
      },
      "body": null,
      "target": "real-device"
    }
  },
  {
    "id": "EVT-0070",
    "timestamp": "2026-02-01T17:21:52.103Z",
    "relativeMs": 4445,
    "type": "action-start",
    "origin": "system",
    "correlationId": "COR-0017",
    "data": {
      "name": "rest.get",
      "component": null,
      "context": {
        "ui": {
          "route": "/config",
          "query": ""
        },
        "platform": "web",
        "featureFlags": {
          "hvsc_enabled": true
        },
        "playback": {
          "queueLength": 0,
          "currentIndex": -1,
          "currentItemId": null,
          "isPlaying": false,
          "elapsedMs": 0,
          "durationMs": null
        },
        "device": {
          "deviceId": null,
          "connectionState": "BUSY"
        }
      }
    }
  },
  {
    "id": "EVT-0071",
    "timestamp": "2026-02-01T17:21:52.134Z",
    "relativeMs": 4476,
    "type": "rest-response",
    "origin": "system",
    "correlationId": "COR-0016",
    "data": {
      "status": 200,
      "body": {
        "categories": [
          "U64 Specific Settings",
          "Audio Mixer",
          "UltiSID Configuration",
          "Drive A Settings",
          "Drive B Settings"
        ],
        "errors": []
      },
      "durationMs": 23,
      "error": null
    }
  },
  {
    "id": "EVT-0072",
    "timestamp": "2026-02-01T17:21:52.134Z",
    "relativeMs": 4476,
    "type": "action-end",
    "origin": "system",
    "correlationId": "COR-0016",
    "data": {
      "status": "success",
      "error": null
    }
  },
  {
    "id": "EVT-0073",
    "timestamp": "2026-02-01T17:21:52.134Z",
    "relativeMs": 4476,
    "type": "backend-decision",
    "origin": "system",
    "correlationId": "COR-0017",
    "data": {
      "selectedTarget": "real-device",
      "reason": "reachable"
    }
  },
  {
    "id": "EVT-0074",
    "timestamp": "2026-02-01T17:21:52.134Z",
    "relativeMs": 4476,
    "type": "rest-request",
    "origin": "system",
    "correlationId": "COR-0017",
    "data": {
      "method": "GET",
      "url": "http://127.0.0.1:37419/v1/info",
      "normalizedUrl": "/v1/info",
      "headers": {
        "Content-Type": "application/json",
        "X-C64U-Host": "127.0.0.1:37419"
      },
      "body": null,
      "target": "real-device"
    }
  },
  {
    "id": "EVT-0075",
    "timestamp": "2026-02-01T17:21:52.310Z",
    "relativeMs": 4652,
    "type": "rest-response",
    "origin": "system",
    "correlationId": "COR-0017",
    "data": {
      "status": 200,
      "body": {
        "product": "C64 Ultimate",
        "firmware_version": "3.12.0",
        "fpga_version": "1.0.0",
        "core_version": "1.0.0",
        "hostname": "c64u",
        "unique_id": "TEST-123",
        "errors": []
      },
      "durationMs": 52,
      "error": null
    }
  },
  {
    "id": "EVT-0076",
    "timestamp": "2026-02-01T17:21:52.310Z",
    "relativeMs": 4652,
    "type": "action-end",
    "origin": "system",
    "correlationId": "COR-0017",
    "data": {
      "status": "success",
      "error": null
    }
  }
]